fergana/__init__.py
fergana/math/__init__.py
fergana/math/functions.py
fergana/math/optimizers.py
fergana/structures/__init__.py
fergana/structures/layers.py
fergana/structures/models.py
fergana/structures/neurons.py
fergana-0.0.1.dist-info/METADATA
fergana-0.0.1.dist-info/WHEEL
fergana-0.0.1.dist-info/RECORD
