Metadata-Version: 2.1
Name: fergana
Version: 0.0.1
Summary: Simple Ml framework
Author: egor-mashtakov
Author-email: egor190707e@gmail.com
Requires-Python: >=3.11,<4.0
Classifier: Programming Language :: Python :: 3
Classifier: Programming Language :: Python :: 3.11
